edgaranalyzer
