Metadata-Version: 2.1
Name: edgar-analyzer
Version: 0.0.1rc6
Summary: Textual analysis on SEC filings from EDGAR
Home-page: https://github.com/mgao6767/edgar-analyzer
Author: Mingze Gao
Author-email: mingze.gao@sydney.edu.au
License: MIT
Classifier: License :: OSI Approved :: MIT License
Classifier: Programming Language :: Python :: 3
Classifier: Programming Language :: Python :: 3.8
Classifier: Intended Audience :: End Users/Desktop
Classifier: Intended Audience :: Financial and Insurance Industry
Classifier: Intended Audience :: Education
Classifier: Intended Audience :: Science/Research
Classifier: Topic :: Scientific/Engineering :: Information Analysis
License-File: LICENSE
